{
    "key": "group_6380cfbbaf33f",
    "title": "Flexible content",
    "fields": [
        {
            "key": "field_6380cfc323927",
            "label": "Blocks",
            "name": "blocks",
            "type": "flexible_content",
            "instructions": "",
            "required": 0,
            "conditional_logic": 0,
            "wrapper": {
                "width": "",
                "class": "",
                "id": ""
            },
            "layouts": {
                "layout_6380cfe7e9aa0": {
                    "key": "layout_6380cfe7e9aa0",
                    "name": "hero_banner",
                    "label": "Hero banner",
                    "display": "block",
                    "sub_fields": [
                        {
                            "key": "field_6380d02723929",
                            "label": "Banner list",
                            "name": "banner_list",
                            "type": "repeater",
                            "instructions": "",
                            "required": 0,
                            "conditional_logic": 0,
                            "wrapper": {
                                "width": "100",
                                "class": "",
                                "id": ""
                            },
                            "collapsed": "",
                            "min": 0,
                            "max": 0,
                            "layout": "block",
                            "button_label": "",
                            "sub_fields": [
                                {
                                    "key": "field_6380d06b2392b",
                                    "label": "Background image",
                                    "name": "background_image",
                                    "type": "image",
                                    "instructions": "",
                                    "required": 0,
                                    "conditional_logic": 0,
                                    "wrapper": {
                                        "width": "30",
                                        "class": "",
                                        "id": ""
                                    },
                                    "return_format": "array",
                                    "preview_size": "medium",
                                    "library": "all",
                                    "min_width": "",
                                    "min_height": "",
                                    "min_size": "",
                                    "max_width": "",
                                    "max_height": "",
                                    "max_size": "",
                                    "mime_types": ""
                                },
                                {
                                    "key": "field_6489b6881349e",
                                    "label": "Logo",
                                    "name": "logo",
                                    "type": "image",
                                    "instructions": "",
                                    "required": 0,
                                    "conditional_logic": 0,
                                    "wrapper": {
                                        "width": "30",
                                        "class": "",
                                        "id": ""
                                    },
                                    "return_format": "array",
                                    "preview_size": "medium",
                                    "library": "all",
                                    "min_width": "",
                                    "min_height": "",
                                    "min_size": "",
                                    "max_width": "",
                                    "max_height": "",
                                    "max_size": "",
                                    "mime_types": ""
                                },
                                {
                                    "key": "field_6380d0512392a",
                                    "label": "Text",
                                    "name": "text",
                                    "type": "textarea",
                                    "instructions": "",
                                    "required": 0,
                                    "conditional_logic": 0,
                                    "wrapper": {
                                        "width": "40",
                                        "class": "",
                                        "id": ""
                                    },
                                    "default_value": "",
                                    "placeholder": "",
                                    "maxlength": "",
                                    "rows": 6,
                                    "new_lines": ""
                                }
                            ]
                        }
                    ],
                    "min": "",
                    "max": ""
                },
                "layout_649444c313b13": {
                    "key": "layout_649444c313b13",
                    "name": "page_banner",
                    "label": "Page banner",
                    "display": "block",
                    "sub_fields": [
                        {
                            "key": "field_649445a313b18",
                            "label": "Page title",
                            "name": "page_title",
                            "type": "text",
                            "instructions": "",
                            "required": 0,
                            "conditional_logic": 0,
                            "wrapper": {
                                "width": "",
                                "class": "",
                                "id": ""
                            },
                            "default_value": "",
                            "placeholder": "",
                            "prepend": "",
                            "append": "",
                            "maxlength": ""
                        },
                        {
                            "key": "field_649444c313b14",
                            "label": "Page banner list",
                            "name": "page_banner_list",
                            "type": "repeater",
                            "instructions": "",
                            "required": 0,
                            "conditional_logic": 0,
                            "wrapper": {
                                "width": "100",
                                "class": "",
                                "id": ""
                            },
                            "collapsed": "",
                            "min": 0,
                            "max": 0,
                            "layout": "block",
                            "button_label": "",
                            "sub_fields": [
                                {
                                    "key": "field_649445d913b19",
                                    "label": "Image",
                                    "name": "image",
                                    "type": "image",
                                    "instructions": "",
                                    "required": 0,
                                    "conditional_logic": 0,
                                    "wrapper": {
                                        "width": "",
                                        "class": "",
                                        "id": ""
                                    },
                                    "return_format": "array",
                                    "preview_size": "medium",
                                    "library": "all",
                                    "min_width": "",
                                    "min_height": "",
                                    "min_size": "",
                                    "max_width": "",
                                    "max_height": "",
                                    "max_size": "",
                                    "mime_types": ""
                                }
                            ]
                        }
                    ],
                    "min": "",
                    "max": ""
                },
                "layout_6380d210b241a": {
                    "key": "layout_6380d210b241a",
                    "name": "text_image",
                    "label": "Text | Image",
                    "display": "block",
                    "sub_fields": [
                        {
                            "key": "field_64899c9654952",
                            "label": "Image position:",
                            "name": "image_position",
                            "type": "radio",
                            "instructions": "",
                            "required": 0,
                            "conditional_logic": 0,
                            "wrapper": {
                                "width": "",
                                "class": "",
                                "id": ""
                            },
                            "choices": {
                                "left": "Image left",
                                "right": "Image right"
                            },
                            "allow_null": 0,
                            "other_choice": 0,
                            "default_value": "",
                            "layout": "vertical",
                            "return_format": "value",
                            "save_other_choice": 0
                        },
                        {
                            "key": "field_6490629af42f6",
                            "label": "Image",
                            "name": "image",
                            "type": "image",
                            "instructions": "",
                            "required": 0,
                            "conditional_logic": 0,
                            "wrapper": {
                                "width": "40",
                                "class": "",
                                "id": ""
                            },
                            "return_format": "array",
                            "preview_size": "medium",
                            "library": "all",
                            "min_width": "",
                            "min_height": "",
                            "min_size": "",
                            "max_width": "",
                            "max_height": "",
                            "max_size": "",
                            "mime_types": ""
                        },
                        {
                            "key": "field_6380d21fb241b",
                            "label": "Text",
                            "name": "text",
                            "type": "wysiwyg",
                            "instructions": "",
                            "required": 0,
                            "conditional_logic": 0,
                            "wrapper": {
                                "width": "60",
                                "class": "",
                                "id": ""
                            },
                            "default_value": "",
                            "tabs": "all",
                            "media_upload": 1,
                            "delay": 0,
                            "toolbar": "full"
                        }
                    ],
                    "min": "",
                    "max": ""
                },
                "layout_6490734074284": {
                    "key": "layout_6490734074284",
                    "name": "text_gallery",
                    "label": "Text | Gallery slider",
                    "display": "block",
                    "sub_fields": [
                        {
                            "key": "field_6490734074285",
                            "label": "Gallery position:",
                            "name": "gallery_position:",
                            "type": "radio",
                            "instructions": "",
                            "required": 0,
                            "conditional_logic": 0,
                            "wrapper": {
                                "width": "",
                                "class": "",
                                "id": ""
                            },
                            "choices": {
                                "left": "Gallery left",
                                "right": "Gallery right"
                            },
                            "allow_null": 0,
                            "other_choice": 0,
                            "default_value": "",
                            "layout": "vertical",
                            "return_format": "value",
                            "save_other_choice": 0
                        },
                        {
                            "key": "field_6490734074286",
                            "label": "Gallery",
                            "name": "gallery",
                            "type": "gallery",
                            "instructions": "",
                            "required": 0,
                            "conditional_logic": 0,
                            "wrapper": {
                                "width": "",
                                "class": "",
                                "id": ""
                            },
                            "return_format": "array",
                            "preview_size": "medium",
                            "insert": "append",
                            "library": "all",
                            "min": "",
                            "max": "",
                            "min_width": "",
                            "min_height": "",
                            "min_size": "",
                            "max_width": "",
                            "max_height": "",
                            "max_size": "",
                            "mime_types": ""
                        },
                        {
                            "key": "field_64907659d2ab4",
                            "label": "Title",
                            "name": "title",
                            "type": "textarea",
                            "instructions": "",
                            "required": 0,
                            "conditional_logic": 0,
                            "wrapper": {
                                "width": "35",
                                "class": "",
                                "id": ""
                            },
                            "default_value": "",
                            "placeholder": "",
                            "maxlength": "",
                            "rows": 4,
                            "new_lines": ""
                        },
                        {
                            "key": "field_64907667d2ab5",
                            "label": "Text",
                            "name": "text",
                            "type": "textarea",
                            "instructions": "",
                            "required": 0,
                            "conditional_logic": 0,
                            "wrapper": {
                                "width": "35",
                                "class": "",
                                "id": ""
                            },
                            "default_value": "",
                            "placeholder": "",
                            "maxlength": "",
                            "rows": 4,
                            "new_lines": ""
                        },
                        {
                            "key": "field_6490743674288",
                            "label": "Button",
                            "name": "button",
                            "type": "link",
                            "instructions": "",
                            "required": 0,
                            "conditional_logic": 0,
                            "wrapper": {
                                "width": "30",
                                "class": "",
                                "id": ""
                            },
                            "return_format": "array"
                        }
                    ],
                    "min": "",
                    "max": ""
                },
                "layout_649181f91ffac": {
                    "key": "layout_649181f91ffac",
                    "name": "subscribe_form",
                    "label": "Subscribe form",
                    "display": "block",
                    "sub_fields": [
                        {
                            "key": "field_649182191ffae",
                            "label": "Title",
                            "name": "title",
                            "type": "textarea",
                            "instructions": "",
                            "required": 0,
                            "conditional_logic": 0,
                            "wrapper": {
                                "width": "50",
                                "class": "",
                                "id": ""
                            },
                            "default_value": "",
                            "placeholder": "",
                            "maxlength": "",
                            "rows": 2,
                            "new_lines": ""
                        },
                        {
                            "key": "field_649183891ffb1",
                            "label": "Form",
                            "name": "form",
                            "type": "acf_cf7",
                            "instructions": "",
                            "required": 0,
                            "conditional_logic": 0,
                            "wrapper": {
                                "width": "50",
                                "class": "",
                                "id": ""
                            }
                        },
                        {
                            "key": "field_6491836f1ffaf",
                            "label": "Text 1",
                            "name": "text_1",
                            "type": "wysiwyg",
                            "instructions": "",
                            "required": 0,
                            "conditional_logic": 0,
                            "wrapper": {
                                "width": "50",
                                "class": "",
                                "id": ""
                            },
                            "default_value": "",
                            "tabs": "all",
                            "media_upload": 1,
                            "delay": 0,
                            "toolbar": "full"
                        },
                        {
                            "key": "field_649183791ffb0",
                            "label": "Text 2",
                            "name": "text_2",
                            "type": "wysiwyg",
                            "instructions": "",
                            "required": 0,
                            "conditional_logic": 0,
                            "wrapper": {
                                "width": "50",
                                "class": "",
                                "id": ""
                            },
                            "default_value": "",
                            "tabs": "all",
                            "media_upload": 1,
                            "delay": 0,
                            "toolbar": "full"
                        }
                    ],
                    "min": "",
                    "max": ""
                },
                "layout_64899e2054953": {
                    "key": "layout_64899e2054953",
                    "name": "information_section",
                    "label": "Information section",
                    "display": "block",
                    "sub_fields": [
                        {
                            "key": "field_64899e2d54954",
                            "label": "Column 1",
                            "name": "column_1",
                            "type": "repeater",
                            "instructions": "",
                            "required": 0,
                            "conditional_logic": 0,
                            "wrapper": {
                                "width": "33",
                                "class": "",
                                "id": ""
                            },
                            "collapsed": "",
                            "min": 0,
                            "max": 0,
                            "layout": "block",
                            "button_label": "",
                            "sub_fields": [
                                {
                                    "key": "field_64899e5454955",
                                    "label": "Title",
                                    "name": "title",
                                    "type": "text",
                                    "instructions": "",
                                    "required": 0,
                                    "conditional_logic": 0,
                                    "wrapper": {
                                        "width": "",
                                        "class": "",
                                        "id": ""
                                    },
                                    "default_value": "",
                                    "placeholder": "",
                                    "prepend": "",
                                    "append": "",
                                    "maxlength": ""
                                },
                                {
                                    "key": "field_64899e8554956",
                                    "label": "Text",
                                    "name": "text",
                                    "type": "textarea",
                                    "instructions": "",
                                    "required": 0,
                                    "conditional_logic": 0,
                                    "wrapper": {
                                        "width": "",
                                        "class": "",
                                        "id": ""
                                    },
                                    "default_value": "",
                                    "placeholder": "",
                                    "maxlength": "",
                                    "rows": 4,
                                    "new_lines": ""
                                }
                            ]
                        },
                        {
                            "key": "field_64899ea454957",
                            "label": "Column 2",
                            "name": "column_2",
                            "type": "repeater",
                            "instructions": "",
                            "required": 0,
                            "conditional_logic": 0,
                            "wrapper": {
                                "width": "33",
                                "class": "",
                                "id": ""
                            },
                            "collapsed": "",
                            "min": 0,
                            "max": 0,
                            "layout": "block",
                            "button_label": "",
                            "sub_fields": [
                                {
                                    "key": "field_64899ea454958",
                                    "label": "Title",
                                    "name": "title",
                                    "type": "text",
                                    "instructions": "",
                                    "required": 0,
                                    "conditional_logic": 0,
                                    "wrapper": {
                                        "width": "",
                                        "class": "",
                                        "id": ""
                                    },
                                    "default_value": "",
                                    "placeholder": "",
                                    "prepend": "",
                                    "append": "",
                                    "maxlength": ""
                                },
                                {
                                    "key": "field_64899ea454959",
                                    "label": "Text",
                                    "name": "text",
                                    "type": "textarea",
                                    "instructions": "",
                                    "required": 0,
                                    "conditional_logic": 0,
                                    "wrapper": {
                                        "width": "",
                                        "class": "",
                                        "id": ""
                                    },
                                    "default_value": "",
                                    "placeholder": "",
                                    "maxlength": "",
                                    "rows": 4,
                                    "new_lines": ""
                                }
                            ]
                        },
                        {
                            "key": "field_64899ea95495a",
                            "label": "Column 3",
                            "name": "column_3",
                            "type": "repeater",
                            "instructions": "",
                            "required": 0,
                            "conditional_logic": 0,
                            "wrapper": {
                                "width": "33",
                                "class": "",
                                "id": ""
                            },
                            "collapsed": "",
                            "min": 0,
                            "max": 0,
                            "layout": "block",
                            "button_label": "",
                            "sub_fields": [
                                {
                                    "key": "field_64899ea95495b",
                                    "label": "Title",
                                    "name": "title",
                                    "type": "text",
                                    "instructions": "",
                                    "required": 0,
                                    "conditional_logic": 0,
                                    "wrapper": {
                                        "width": "",
                                        "class": "",
                                        "id": ""
                                    },
                                    "default_value": "",
                                    "placeholder": "",
                                    "prepend": "",
                                    "append": "",
                                    "maxlength": ""
                                },
                                {
                                    "key": "field_64899ea95495c",
                                    "label": "Text",
                                    "name": "text",
                                    "type": "textarea",
                                    "instructions": "",
                                    "required": 0,
                                    "conditional_logic": 0,
                                    "wrapper": {
                                        "width": "",
                                        "class": "",
                                        "id": ""
                                    },
                                    "default_value": "",
                                    "placeholder": "",
                                    "maxlength": "",
                                    "rows": 4,
                                    "new_lines": ""
                                }
                            ]
                        }
                    ],
                    "min": "",
                    "max": ""
                },
                "layout_6489b3077c48e": {
                    "key": "layout_6489b3077c48e",
                    "name": "hero_section",
                    "label": "Hero section",
                    "display": "block",
                    "sub_fields": [
                        {
                            "key": "field_6489b3147c48f",
                            "label": "Image",
                            "name": "image",
                            "type": "image",
                            "instructions": "",
                            "required": 0,
                            "conditional_logic": 0,
                            "wrapper": {
                                "width": "50",
                                "class": "",
                                "id": ""
                            },
                            "return_format": "array",
                            "preview_size": "medium",
                            "library": "all",
                            "min_width": "",
                            "min_height": "",
                            "min_size": "",
                            "max_width": "",
                            "max_height": "",
                            "max_size": "",
                            "mime_types": ""
                        },
                        {
                            "key": "field_6489b3437c490",
                            "label": "Text",
                            "name": "text",
                            "type": "wysiwyg",
                            "instructions": "",
                            "required": 0,
                            "conditional_logic": 0,
                            "wrapper": {
                                "width": "",
                                "class": "",
                                "id": ""
                            },
                            "default_value": "",
                            "tabs": "all",
                            "media_upload": 1,
                            "delay": 0,
                            "toolbar": "full"
                        }
                    ],
                    "min": "",
                    "max": ""
                },
                "layout_6489b76110fc8": {
                    "key": "layout_6489b76110fc8",
                    "name": "text_section",
                    "label": "Text section",
                    "display": "block",
                    "sub_fields": [
                        {
                            "key": "field_6489b76b10fc9",
                            "label": "Text",
                            "name": "text",
                            "type": "wysiwyg",
                            "instructions": "",
                            "required": 0,
                            "conditional_logic": 0,
                            "wrapper": {
                                "width": "",
                                "class": "",
                                "id": ""
                            },
                            "default_value": "",
                            "tabs": "all",
                            "media_upload": 1,
                            "delay": 0,
                            "toolbar": "full"
                        }
                    ],
                    "min": "",
                    "max": ""
                },
                "layout_6489b85510fca": {
                    "key": "layout_6489b85510fca",
                    "name": "about_section",
                    "label": "About section",
                    "display": "block",
                    "sub_fields": [
                        {
                            "key": "field_6489b86010fcb",
                            "label": "Image",
                            "name": "image",
                            "type": "image",
                            "instructions": "",
                            "required": 0,
                            "conditional_logic": 0,
                            "wrapper": {
                                "width": "50",
                                "class": "",
                                "id": ""
                            },
                            "return_format": "array",
                            "preview_size": "medium",
                            "library": "all",
                            "min_width": "",
                            "min_height": "",
                            "min_size": "",
                            "max_width": "",
                            "max_height": "",
                            "max_size": "",
                            "mime_types": ""
                        },
                        {
                            "key": "field_6489b88510fcc",
                            "label": "Text",
                            "name": "text",
                            "type": "wysiwyg",
                            "instructions": "",
                            "required": 0,
                            "conditional_logic": 0,
                            "wrapper": {
                                "width": "50",
                                "class": "",
                                "id": ""
                            },
                            "default_value": "",
                            "tabs": "all",
                            "media_upload": 1,
                            "delay": 0,
                            "toolbar": "full"
                        },
                        {
                            "key": "field_6489b89510fcd",
                            "label": "Button",
                            "name": "button",
                            "type": "link",
                            "instructions": "",
                            "required": 0,
                            "conditional_logic": 0,
                            "wrapper": {
                                "width": "",
                                "class": "",
                                "id": ""
                            },
                            "return_format": "array"
                        }
                    ],
                    "min": "",
                    "max": ""
                },
                "layout_6489bbba35c74": {
                    "key": "layout_6489bbba35c74",
                    "name": "product_qualities",
                    "label": "Product qualities",
                    "display": "block",
                    "sub_fields": [
                        {
                            "key": "field_6489bbc735c75",
                            "label": "Image",
                            "name": "image",
                            "type": "image",
                            "instructions": "",
                            "required": 0,
                            "conditional_logic": 0,
                            "wrapper": {
                                "width": "50",
                                "class": "",
                                "id": ""
                            },
                            "return_format": "array",
                            "preview_size": "medium",
                            "library": "all",
                            "min_width": "",
                            "min_height": "",
                            "min_size": "",
                            "max_width": "",
                            "max_height": "",
                            "max_size": "",
                            "mime_types": ""
                        },
                        {
                            "key": "field_6489bbde35c76",
                            "label": "Text",
                            "name": "text",
                            "type": "wysiwyg",
                            "instructions": "",
                            "required": 0,
                            "conditional_logic": 0,
                            "wrapper": {
                                "width": "50",
                                "class": "",
                                "id": ""
                            },
                            "default_value": "",
                            "tabs": "all",
                            "media_upload": 1,
                            "delay": 0,
                            "toolbar": "full"
                        }
                    ],
                    "min": "",
                    "max": ""
                }
            },
            "button_label": "Add Section",
            "min": "",
            "max": ""
        }
    ],
    "location": [
        [
            {
                "param": "post_type",
                "operator": "==",
                "value": "page"
            }
        ],
        [
            {
                "param": "post_type",
                "operator": "==",
                "value": "rooms-and-suites"
            }
        ]
    ],
    "menu_order": 0,
    "position": "normal",
    "style": "default",
    "label_placement": "top",
    "instruction_placement": "label",
    "hide_on_screen": "",
    "active": true,
    "description": "",
    "show_in_rest": 0,
    "modified": 1687438831
}